napari_mask_density/__init__.py
napari_mask_density/_version.py
napari_mask_density/_widget.py
napari_mask_density/napari.yaml
napari_mask_density-0.1.dist-info/licenses/LICENSE
napari_mask_density-0.1.dist-info/METADATA
napari_mask_density-0.1.dist-info/WHEEL
napari_mask_density-0.1.dist-info/entry_points.txt
napari_mask_density-0.1.dist-info/top_level.txt
napari_mask_density-0.1.dist-info/RECORD
